{
    "name": "blob_report_user_details",
    "properties": {
        "linkedServiceName": {
            "referenceName": "idpay-report-trx-blob-storage-ls",
            "type": "LinkedServiceReference"
        },
        "parameters": {
            "initiativeId": {
                "type": "String"
            },
            "reportName": {
                "type": "String"
            }
        },
        "annotations": [],
        "type": "DelimitedText",
        "typeProperties": {
            "location": {
                "type": "AzureBlobStorageLocation",
                "fileName": {
                    "value": "@dataset().reportName",
                    "type": "Expression"
                },
                "folderPath": {
                    "value": "@concat('initiative/',dataset().initiativeId, '/report')",
                    "type": "Expression"
                },
                "container": "report-user-details"
            },
            "columnDelimiter": ";",
            "escapeChar": "\\",
            "firstRowAsHeader": true,
            "quoteChar": "\""
        },
        "schema": []
    },
    "type": "Microsoft.DataFactory/factories/datasets"
}
